sidereal.cpython-312-darwin.so
sidereal-0.0.16.dist-info/RECORD
sidereal-0.0.16.dist-info/WHEEL
sidereal-0.0.16.dist-info/top_level.txt
sidereal-0.0.16.dist-info/METADATA
