Metadata-Version: 2.1
Name: sidereal
Version: 0.0.16
Summary: Time and coordinate systems for astrodynamics
Author-email: Liam Robinson <liamers127@gmail.com>
Project-URL: Repository, https://github.com/liamrobinson1/sidereal
Requires-Python: >=3.10
